README.txt
setup.py
addremoveoptions/__init__.py
addremoveoptions/release.py
addremoveoptions/widgets.py
addremoveoptions.egg-info/PKG-INFO
addremoveoptions.egg-info/SOURCES.txt
addremoveoptions.egg-info/dependency_links.txt
addremoveoptions.egg-info/entry_points.txt
addremoveoptions.egg-info/not-zip-safe
addremoveoptions.egg-info/paster_plugins.txt
addremoveoptions.egg-info/requires.txt
addremoveoptions.egg-info/sqlobject.txt
addremoveoptions.egg-info/top_level.txt
addremoveoptions/templates/__init__.py