Metadata-Version: 1.0
Name: addremoveoptions
Version: 1.0
Summary: Turbogears widget that creates a selectbox in whic you can add and remove options
Home-page: http://turbogears.org/
Author: Abhishek Kumar
Author-email: abhicoo@gmail.com
License: UNKNOWN
Download-URL: http://turbogears.org/widgets/
Keywords: turbogears.widgets
Platform: UNKNOWN
Classifier: Development Status :: 3 - Alpha
Classifier: Operating System :: OS Independent
Classifier: Programming Language :: Python
Classifier: Topic :: Software Development :: Libraries :: Python Modules
Classifier: Framework :: TurboGears
Classifier: Framework :: TurboGears :: Widgets
